CDmetrics/CDdm.py
CDmetrics/CDmc.py
CDmetrics/CDpu.py
CDmetrics/__init__.py
CDmetrics/nn.py
CDmetrics/utils.py
cdmetrics-0.1.7.dist-info/LICENSE
cdmetrics-0.1.7.dist-info/METADATA
cdmetrics-0.1.7.dist-info/WHEEL
cdmetrics-0.1.7.dist-info/top_level.txt
cdmetrics-0.1.7.dist-info/RECORD
