Metadata-Version: 2.1
Name: cdmetrics
Version: 0.1.7
Summary: Calculate case difficulty within datasets
Author-email: Eulee Kwon <euleekwon@gmail.com>, Yves Nsoga <nsogan@gmail.com>
Project-URL: homepage, https://cumming.ucalgary.ca/lab/dih/projects/current-projects/development-novel-case-specific-machine-learning-methodologies
Project-URL: repository, https://github.com/data-intelligence-for-health-lab/CDmetrics.git
Keywords: data_difficulty,case_difficulty,instance_hardness,difficulty
Classifier: License :: OSI Approved :: MIT License
Classifier: Programming Language :: Python :: 3.9
Classifier: Operating System :: OS Independent
Requires-Python: >=3.9
License-File: LICENSE
Requires-Dist: pandas
Requires-Dist: scikit-learn
Requires-Dist: tensorflow
Requires-Dist: tqdm
Requires-Dist: ray==2.11.0
Requires-Dist: ray[train]
